{"name":"kraj związkowy Szlezwik-Holsztyn","slug":"kraj-zwiazkowy-szlezwik-holsztyn","extremes":{"north":"54.514410686386","east":"9.5618852677291","south":"54.514410686386","west":"9.5618852677291"},"breweries":[{"id":463,"name":"Asgaard Brauerei Schleswig","altName":"","slug":"asgaard-brauerei-schleswig","location":{"country":{"name":"Niemcy","symbol":"de","slug":"niemcy"},"coordinates":["9.561885","54.514411"],"city":{"name":"Schleswig","translation":"Szlezwik","slug":"schleswig","country":{"name":"Niemcy","symbol":"de","slug":"niemcy"},"breweries":1,"trips":1},"address":"Königstraße 27"},"date":"sierpień 2024"}],"counters":{"breweries":1,"trips":1,"cities":1,"countries":1}}