{"name":"województwo kujawsko-pomorskie","slug":"wojewodztwo-kujawsko-pomorskie","extremes":{"north":"53.467805","east":"17.738829","south":"52.849280","west":"18.741736"},"breweries":[{"id":91,"name":"Jan Olbracht Browar Staromiejski","slug":"jan-olbracht-browar-staromiejski","location":{"country":{"name":"Polska","symbol":"pl","slug":"polska"},"coordinates":["18.605791","53.011100"],"city":{"name":"Toruń","translation":"","slug":"torun","country":{"name":"Polska","symbol":"pl","slug":"polska"},"breweries":1,"trips":1},"address":"Szczytna 15"},"date":"wrzesień 2018"},{"id":253,"name":"Stacja Filtracja","slug":"stacja-filtracja","location":{"country":{"name":"Polska","symbol":"pl","slug":"polska"},"coordinates":["17.738829","52.849280"],"city":{"name":"Żnin","translation":"","slug":"znin","country":{"name":"Polska","symbol":"pl","slug":"polska"},"breweries":1,"trips":1},"address":"Janickiego 1"},"date":"lipiec 2021"},{"id":262,"name":"Browar Grudziądz","slug":"browar-grudziadz","location":{"country":{"name":"Polska","symbol":"pl","slug":"polska"},"coordinates":["18.741736","53.467805"],"city":{"name":"Grudziądz","translation":"","slug":"grudziadz","country":{"name":"Polska","symbol":"pl","slug":"polska"},"breweries":1,"trips":1},"address":"Chełmińska 144"},"date":"lipiec 2021"}],"counters":{"breweries":3,"trips":2,"cities":3,"countries":1}}