{"name":"Liptovský Mikuláš","translation":"Liptowski Mikułasz","extremes":{"north":"49.081826684939","east":"19.617414418472","south":"49.08094963822","west":"19.627133354149"},"breweries":[{"id":642,"name":"Nealkoholický pivovar Nilio","altName":"","slug":"nealkoholicky-pivovar-nilio","location":{"country":{"name":"Słowacja","symbol":"sk","slug":"slowacja"},"coordinates":["19.627133","49.081827"],"city":{"name":"Liptovský Mikuláš","translation":"Liptowski Mikułasz","slug":"liptovsky-mikulas","country":{"name":"Słowacja","symbol":"sk","slug":"slowacja"},"breweries":2,"trips":2},"address":"Družstevná 5"},"date":"grudzień 2025"},{"id":363,"name":"Pivovar a pivovarská reštaurácia Liptovar","altName":"","slug":"pivovar-a-pivovarska-restauracia-liptovar","location":{"country":{"name":"Słowacja","symbol":"sk","slug":"slowacja"},"coordinates":["19.617414","49.080950"],"city":{"name":"Liptovský Mikuláš","translation":"Liptowski Mikułasz","slug":"liptovsky-mikulas","country":{"name":"Słowacja","symbol":"sk","slug":"slowacja"},"breweries":2,"trips":2},"address":"Garbiarska 2032"},"date":"sierpień 2022"}]}