{"name":"Savudrija","translation":"","extremes":{"north":"45.487747281487","east":"13.521155719657","south":"45.487747281487","west":"13.521155719657"},"breweries":[{"id":339,"name":"Vergal Brewery","slug":"vergal-brewery","location":{"country":{"name":"Chrowacja","symbol":"hr","slug":"chrowacja"},"coordinates":["13.521156","45.487747"],"city":{"name":"Savudrija","translation":"","slug":"savudrija","country":{"name":"Chrowacja","symbol":"hr","slug":"chrowacja"},"breweries":1,"trips":1},"address":"Frančeskija 52 i"},"date":"czerwiec 2022"}]}