{"label":"październik 2025","slug":"10","extremes":{"north":"52.20834667435","east":"16.747032914019","south":"51.709076099575","west":"17.489147498691"},"breweries":[{"id":628,"name":"Browar Fortuna","altName":"","slug":"browar-fortuna","location":{"country":{"name":"Polska","symbol":"pl","slug":"polska"},"coordinates":["17.489147","52.205399"],"city":{"name":"Miłosław","translation":"","slug":"miloslaw","country":{"name":"Polska","symbol":"pl","slug":"polska"},"breweries":1,"trips":1},"address":"Wrzesińska 24"},"date":"październik 2025"},{"id":629,"name":"Browar Gzub","altName":"","slug":"browar-gzub","location":{"country":{"name":"Polska","symbol":"pl","slug":"polska"},"coordinates":["17.200507","52.208347"],"city":{"name":"Annopole","translation":"","slug":"annopole","country":{"name":"Polska","symbol":"pl","slug":"polska"},"breweries":1,"trips":1},"address":"Annopole 9a"},"date":"październik 2025"},{"id":630,"name":"Browar Bojanowo","altName":"","slug":"browar-bojanowo","location":{"country":{"name":"Polska","symbol":"pl","slug":"polska"},"coordinates":["16.747033","51.709076"],"city":{"name":"Bojanowo","translation":"","slug":"bojanowo","country":{"name":"Polska","symbol":"pl","slug":"polska"},"breweries":1,"trips":1},"address":"Browarowa 2"},"date":"październik 2025"}],"counters":{"breweries":3,"countries":1,"trips":1,"cities":3}}