{"id":"72","name":"Beaver Brewing Company","slug":"beaver-brewing-company","note":"","location":{"country":{"name":"Austria","symbol":"at","slug":"austria"},"coordinates":["16.356967","48.224593"],"city":{"name":"Wien","translation":"Wiedeń","slug":"wien","country":{"name":"Austria","symbol":"at","slug":"austria"},"breweries":11,"trips":3},"address":"Liechtensteinstraße 69"},"date":{"label":"23 lipca 2017","year":"2017","month":"07"},"trip":{"name":"wyjazd do Włoch, wakacje 2017","slug":"wyjazd-do-wloch-wakacje-2017"},"tags":{"browar-restauracyjny":{"name":"browar restauracyjny","slug":"browar-restauracyjny","breweries":182},"obejrzany-sprzet":{"name":"obejrzany sprzęt","slug":"obejrzany-sprzet","breweries":231},"piwo-sprobowane-na-miejscu":{"name":"piwo spróbowane na miejscu","slug":"piwo-sprobowane-na-miejscu","breweries":224}}}