{"id":"338","name":"Brauerei Puntigam","altName":null,"slug":"brauerei-puntigam","note":"","location":{"country":{"name":"Austria","symbol":"at","slug":"austria"},"coordinates":["15.433327","47.029861"],"city":{"name":"Graz","translation":"","slug":"graz","country":{"name":"Austria","symbol":"at","slug":"austria"},"breweries":1,"trips":1},"address":"Triester Str. 357-359"},"date":{"label":"20 czerwca 2022","year":"2022","month":"06"},"trip":{"name":"wakacje 2022","slug":"wakacje-2022"},"tags":{"browar-koncernowy":{"name":"browar koncernowy","slug":"browar-koncernowy","breweries":13},"europa":{"name":"Europa","slug":"europa","breweries":580},"koncern-brau-union":{"name":"koncern Brau Union","slug":"koncern-brau-union","breweries":1},"panstwa-niemieckojezyczne":{"name":"państwa niemieckojęzyczne","slug":"panstwa-niemieckojezyczne","breweries":101},"panstwa-unii-europejskiej":{"name":"państwa Unii Europejskiej","slug":"panstwa-unii-europejskiej","breweries":461},"piwo-sprobowane-poza-browarem":{"name":"piwo spróbowane poza browarem","slug":"piwo-sprobowane-poza-browarem","breweries":75},"przybrowarniany-sklep":{"name":"przybrowarniany sklep","slug":"przybrowarniany-sklep","breweries":64}}}