{"id":"590","name":"Browar Podborze","altName":null,"slug":"browar-podborze","note":"","location":{"country":{"name":"Polska","symbol":"pl","slug":"polska"},"coordinates":["21.929215","52.821428"],"city":{"name":"Podborze","translation":"","slug":"podborze","country":{"name":"Polska","symbol":"pl","slug":"polska"},"breweries":1,"trips":1},"address":"Zambrowska 43"},"date":{"label":"21 lipca 2025","year":"2025","month":"07"},"trip":{"name":"wakacje 2025","slug":"wakacje-2025"},"tags":{"browar-restauracyjny":{"name":"browar restauracyjny","slug":"browar-restauracyjny","breweries":266},"europa":{"name":"Europa","slug":"europa","breweries":557},"obejrzany-sprzet":{"name":"obejrzany sprzęt","slug":"obejrzany-sprzet","breweries":545},"panstwa-unii-europejskiej":{"name":"państwa Unii Europejskiej","slug":"panstwa-unii-europejskiej","breweries":438},"piwo-sprobowane-na-miejscu":{"name":"piwo spróbowane na miejscu","slug":"piwo-sprobowane-na-miejscu","breweries":509},"piwo-sprobowane-poza-browarem":{"name":"piwo spróbowane poza browarem","slug":"piwo-sprobowane-poza-browarem","breweries":71},"spotkanie-z-piwowarem":{"name":"spotkanie z piwowarem","slug":"spotkanie-z-piwowarem","breweries":112},"wojewodztwo-mazowieckie":{"name":"województwo mazowieckie","slug":"wojewodztwo-mazowieckie","breweries":7}}}