{"id":"20","name":"Pivovar Rychnov nad Kněžnou","slug":"pivovar-rychnov-nad-kneznou","note":"","location":{"country":{"name":"Czechy","symbol":"cz","slug":"czechy"},"coordinates":["16.278665","50.171188"],"city":{"name":"Rychnov nad Kněžnou","translation":"","slug":"rychnov-nad-kneznou","country":{"name":"Czechy","symbol":"cz","slug":"czechy"},"breweries":1,"trips":1},"address":"Kaštany 435"},"date":{"label":"17 października 2015","year":"2015","month":"10"},"trip":{"name":"kraj hradecki, październik 2015","slug":"kraj-hradecki-pazdziernik-2015"},"tags":{"browar-restauracyjny":{"name":"browar restauracyjny","slug":"browar-restauracyjny","breweries":177},"instalacja-mbs":{"name":"instalacja MBS","slug":"instalacja-mbs","breweries":7},"kraj-hradecki":{"name":"kraj hradecki","slug":"kraj-hradecki","breweries":8},"obejrzany-sprzet":{"name":"obejrzany sprzęt","slug":"obejrzany-sprzet","breweries":239},"piwo-sprobowane-na-miejscu":{"name":"piwo spróbowane na miejscu","slug":"piwo-sprobowane-na-miejscu","breweries":246},"piwo-sprobowane-poza-browarem":{"name":"piwo spróbowane poza browarem","slug":"piwo-sprobowane-poza-browarem","breweries":39}}}