{"id":"47","name":"Pracownia Piwa","altName":null,"slug":"pracownia-piwa","note":"","location":{"country":{"name":"Polska","symbol":"pl","slug":"polska"},"coordinates":["19.838354","50.108962"],"city":{"name":"Modlniczka","translation":"","slug":"modlniczka","country":{"name":"Polska","symbol":"pl","slug":"polska"},"breweries":1,"trips":1},"address":"Kasztanowa 31"},"date":{"label":"9 września 2016","year":"2016","month":"09"},"trip":{"name":"Kraków i okolice, wrzesień 2016","slug":"krakow-i-okolice-wrzesien-2016"},"tags":{"browar":{"name":"browar","slug":"browar","breweries":667},"degustacja-na-miejscu":{"name":"degustacja na miejscu","slug":"degustacja-na-miejscu","breweries":544},"degustacja-poza-odwiedzinami":{"name":"degustacja poza odwiedzinami","slug":"degustacja-poza-odwiedzinami","breweries":86},"europa":{"name":"Europa","slug":"europa","breweries":604},"mikrobrowar":{"name":"mikrobrowar","slug":"mikrobrowar","breweries":134},"obecnie-zamkniety":{"name":"obecnie zamknięty","slug":"obecnie-zamkniety","breweries":50},"obejrzany-sprzet":{"name":"obejrzany sprzęt","slug":"obejrzany-sprzet","breweries":583},"panstwa-unii-europejskiej":{"name":"państwa Unii Europejskiej","slug":"panstwa-unii-europejskiej","breweries":463},"sklep":{"name":"sklep","slug":"sklep","breweries":74},"spotkanie-z-piwowarem":{"name":"spotkanie z piwowarem","slug":"spotkanie-z-piwowarem","breweries":116},"wojewodztwo-malopolskie":{"name":"województwo małopolskie","slug":"wojewodztwo-malopolskie","breweries":17}}}