{"id":"193","name":"Starosloviensky pivovar","slug":"starosloviensky-pivovar","note":"","location":{"country":{"name":"Słowacja","symbol":"sk","slug":"slowacja"},"coordinates":["17.110637","48.148954"],"city":{"name":"Bratislava","slug":"bratislava","country":{"name":"Słowacja","symbol":"sk","slug":"slowacja"},"breweries":8,"trips":1},"address":"Vysoká 4260\/15"},"date":{"label":"19 października 2019","year":"2019","month":"10"},"trip":{"name":"Czechy, Austria i Słowacja, październik 2019","slug":"czechy-austria-i-slowacja-pazdziernik-2019"},"tags":{"browar-restauracyjny":{"name":"browar restauracyjny","slug":"browar-restauracyjny","breweries":170},"piwo-sprobowane-na-miejscu":{"name":"piwo spróbowane na miejscu","slug":"piwo-sprobowane-na-miejscu","breweries":215}}}