{"id":"323","name":"The Newcastle Gin Company","altName":null,"slug":"the-newcastle-gin-company","note":"","location":{"country":{"name":"Wielka Brytania","symbol":"gb","slug":"wielka-brytania"},"coordinates":["-1.618420","54.973958"],"city":{"name":"Newcastle upon Tyne","translation":"","slug":"newcastle-upon-tyne","country":{"name":"Wielka Brytania","symbol":"gb","slug":"wielka-brytania"},"breweries":10,"trips":1},"address":"Bealim House, 17-25 Gallowgate"},"date":{"label":"25 marca 2022","year":"2022","month":"03"},"trip":{"name":"hrabstwo Tyne and Wear, marzec 2022","slug":"hrabstwo-tyne-and-wear-marzec-2022"},"tags":{"anglia":{"name":"Anglia","slug":"anglia","breweries":94},"degustacja-na-miejscu":{"name":"degustacja na miejscu","slug":"degustacja-na-miejscu","breweries":544},"destylarnia":{"name":"destylarnia","slug":"destylarnia","breweries":27},"destylarnia-ginu":{"name":"destylarnia ginu","slug":"destylarnia-ginu","breweries":2},"europa":{"name":"Europa","slug":"europa","breweries":604},"odwiedzone-podczas-dziadotripu":{"name":"odwiedzone podczas dziadotripu","slug":"odwiedzone-podczas-dziadotripu","breweries":128},"panstwa-anglojezyczne":{"name":"państwa anglojęzyczne","slug":"panstwa-anglojezyczne","breweries":173}}}