{"name":"Jedlina-Zdrój, majówka 2018","slug":"jedlina-zdroj-majowka-2018","extremes":{"north":"50.713068","east":"16.358363","south":"50.713068","west":"16.358363"},"counters":{"breweries":1,"countries":1,"cities":1},"breweries":{"browar-jedlinka":{"id":80,"name":"Browar Jedlinka","slug":"browar-jedlinka","location":{"country":{"name":"Polska","symbol":"pl","slug":"polska"},"coordinates":["16.358363","50.713068"],"city":{"name":"Jedlina-Zdrój","translation":"","slug":"jedlina-zdroj","country":{"name":"Polska","symbol":"pl","slug":"polska"},"breweries":1,"trips":1},"address":"Zamkowa 3"},"date":"maj 2018"}},"countries":{"polska":{"name":"Polska","symbol":"pl","slug":"polska","breweriesCount":116}}}