{"name":"Kaszuby, lipiec 2021","slug":"kaszuby-lipiec-2021","extremes":{"north":"54.513943","east":"17.598659","south":"52.536957","west":"18.741736"},"counters":{"breweries":11,"countries":1,"cities":8},"breweries":{"dobry-browar":{"id":252,"name":"Dobry Browar","slug":"dobry-browar","location":{"country":{"name":"Polska","symbol":"pl","slug":"polska"},"coordinates":["17.598659","52.536957"],"city":{"name":"Gniezno","translation":"","slug":"gniezno","country":{"name":"Polska","symbol":"pl","slug":"polska"},"breweries":1,"trips":1},"address":"Grzybowo 34"},"date":"lipiec 2021"},"stacja-filtracja":{"id":253,"name":"Stacja Filtracja","slug":"stacja-filtracja","location":{"country":{"name":"Polska","symbol":"pl","slug":"polska"},"coordinates":["17.738829","52.849280"],"city":{"name":"Żnin","translation":"","slug":"znin","country":{"name":"Polska","symbol":"pl","slug":"polska"},"breweries":1,"trips":1},"address":"Janickiego 1"},"date":"lipiec 2021"},"browar-vrest":{"id":254,"name":"Browar Vrest","slug":"browar-vrest","location":{"country":{"name":"Polska","symbol":"pl","slug":"polska"},"coordinates":["18.588509","54.380895"],"city":{"name":"Gdańsk","translation":"","slug":"gdansk","country":{"name":"Polska","symbol":"pl","slug":"polska"},"breweries":5,"trips":2},"address":"Słowackiego 23"},"date":"lipiec 2021"},"browar-pg4":{"id":255,"name":"Browar PG4","slug":"browar-pg4","location":{"country":{"name":"Polska","symbol":"pl","slug":"polska"},"coordinates":["18.644651","54.354194"],"city":{"name":"Gdańsk","translation":"","slug":"gdansk","country":{"name":"Polska","symbol":"pl","slug":"polska"},"breweries":5,"trips":2},"address":"Podwale Grodzkie 4"},"date":"lipiec 2021"},"hola-tapas":{"id":256,"name":"Hola Tapas","slug":"hola-tapas","location":{"country":{"name":"Polska","symbol":"pl","slug":"polska"},"coordinates":["18.651683","54.350045"],"city":{"name":"Gdańsk","translation":"","slug":"gdansk","country":{"name":"Polska","symbol":"pl","slug":"polska"},"breweries":5,"trips":2},"address":"Piwna 50\/51"},"date":"lipiec 2021"},"browar-kaszebsko-koruna":{"id":257,"name":"Browar Kaszëbskô Kóruna","slug":"browar-kaszebsko-koruna","location":{"country":{"name":"Polska","symbol":"pl","slug":"polska"},"coordinates":["18.107024","54.205116"],"city":{"name":"Szymbark","translation":"","slug":"szymbark","country":{"name":"Polska","symbol":"pl","slug":"polska"},"breweries":1,"trips":1},"address":"Szymbarskich Zakładników 12"},"date":"lipiec 2021"},"browar-lubrow":{"id":258,"name":"Browar Lubrow","slug":"browar-lubrow","location":{"country":{"name":"Polska","symbol":"pl","slug":"polska"},"coordinates":["18.294328","54.273724"],"city":{"name":"Borcz","translation":"","slug":"borcz","country":{"name":"Polska","symbol":"pl","slug":"polska"},"breweries":1,"trips":1},"address":"Borcz 2"},"date":"lipiec 2021"},"browar-port-gdynia":{"id":259,"name":"Browar Port Gdynia","slug":"browar-port-gdynia","location":{"country":{"name":"Polska","symbol":"pl","slug":"polska"},"coordinates":["18.549998","54.513943"],"city":{"name":"Gdynia","translation":"","slug":"gdynia","country":{"name":"Polska","symbol":"pl","slug":"polska"},"breweries":1,"trips":1},"address":"Bulwar Nadmorski 2"},"date":"lipiec 2021"},"browar-miejski-sopot":{"id":260,"name":"Browar Miejski Sopot","slug":"browar-miejski-sopot","location":{"country":{"name":"Polska","symbol":"pl","slug":"polska"},"coordinates":["18.563523","54.443458"],"city":{"name":"Sopot","translation":"","slug":"sopot","country":{"name":"Polska","symbol":"pl","slug":"polska"},"breweries":1,"trips":1},"address":"Bohaterów Monte Cassino 35"},"date":"lipiec 2021"},"piwnica-rajcow":{"id":261,"name":"Piwnica Rajców","slug":"piwnica-rajcow","location":{"country":{"name":"Polska","symbol":"pl","slug":"polska"},"coordinates":["18.653270","54.348746"],"city":{"name":"Gdańsk","translation":"","slug":"gdansk","country":{"name":"Polska","symbol":"pl","slug":"polska"},"breweries":5,"trips":2},"address":"Długi Targ 44"},"date":"lipiec 2021"},"browar-grudziadz":{"id":262,"name":"Browar Grudziądz","slug":"browar-grudziadz","location":{"country":{"name":"Polska","symbol":"pl","slug":"polska"},"coordinates":["18.741736","53.467805"],"city":{"name":"Grudziądz","translation":"","slug":"grudziadz","country":{"name":"Polska","symbol":"pl","slug":"polska"},"breweries":1,"trips":1},"address":"Chełmińska 144"},"date":"lipiec 2021"}},"countries":{"polska":{"name":"Polska","symbol":"pl","slug":"polska","breweriesCount":108}}}