{"name":"Web Summit 2025","slug":"web-summit-2025","extremes":{"north":"38.738918859214","east":"-9.1404863391531","south":"38.73402330314","west":"-9.1042920679821"},"counters":{"breweries":2,"countries":1,"cities":1},"breweries":{"fermentage":{"id":640,"name":"Fermentage","altName":"","slug":"fermentage","location":{"country":{"name":"Portugalia","symbol":"pt","slug":"portugalia"},"coordinates":["-9.104292","38.738919"],"city":{"name":"Lisboa","translation":"Lizbona","slug":"lisboa","country":{"name":"Portugalia","symbol":"pt","slug":"portugalia"},"breweries":2,"trips":1},"address":"R. Cap. Leitão 1B"},"date":"listopad 2025"},"lx-brewery":{"id":641,"name":"LX Brewery","altName":"","slug":"lx-brewery","location":{"country":{"name":"Portugalia","symbol":"pt","slug":"portugalia"},"coordinates":["-9.140486","38.734023"],"city":{"name":"Lisboa","translation":"Lizbona","slug":"lisboa","country":{"name":"Portugalia","symbol":"pt","slug":"portugalia"},"breweries":2,"trips":1},"address":"R. do Funchal n5"},"date":"listopad 2025"}},"countries":{"portugalia":{"name":"Portugalia","symbol":"pt","slug":"portugalia","breweriesCount":2}}}